constants_set/__init__.py
constants_set/sets.py
constants_set-0.5.dist-info/METADATA
constants_set-0.5.dist-info/WHEEL
constants_set-0.5.dist-info/top_level.txt
constants_set-0.5.dist-info/RECORD
