Metadata-Version: 2.1
Name: constants-set
Version: 0.5
Summary: Simple constants sets for Python
Home-page: https://github.com/raphael-leger/constants-set
Author: Raphaël Léger
Author-email: raphael+pypi@nodixo.com
License: MIT
Platform: UNKNOWN
